nr/__init__.py
nr/config/__init__.py
nr/config/jinja.py
nr/config/py.typed
nr/config/reloader.py
nr/config/transform.py
nr/config/util.py
nr/config/loaders/__init__.py
nr/config/loaders/test_yaml.py
nr/config/loaders/yaml.py
nr.config-0.2.0.dist-info/LICENSE.txt
nr.config-0.2.0.dist-info/METADATA
nr.config-0.2.0.dist-info/WHEEL
nr.config-0.2.0.dist-info/top_level.txt
nr.config-0.2.0.dist-info/RECORD
