Metadata-Version: 2.1
Name: nr.config
Version: 0.2.0
Summary: Utility library to implement composable YAML configuration files.
Home-page: https://git.niklasrosenstein.com/NiklasRosenstein/nr
Author: Niklas Rosenstein
Author-email: rosensteinniklas@gmail.com
License: MIT
Platform: UNKNOWN
Requires-Python: >=3.4.0,<4.0.0
Requires-Dist: dataclasses (<1.0.0,>=0.6.0)
Requires-Dist: nr.collections (<0.2.0,>=0.1.1)
Requires-Dist: nr.pylang.utils (<0.2.0,>=0.1.1)
Requires-Dist: six (<2.0.0,>=1.14.0)
Requires-Dist: Jinja2 (<3.0.0,>=2.11.2)
